airbyte/__init__.py
airbyte/_batch_handles.py
airbyte/_connector_base.py
airbyte/_executors/__init__.py
airbyte/_executors/base.py
airbyte/_executors/declarative.py
airbyte/_executors/docker.py
airbyte/_executors/local.py
airbyte/_executors/python.py
airbyte/_executors/util.py
airbyte/_message_iterators.py
airbyte/_processors/__init__.py
airbyte/_processors/sql/__init__.py
airbyte/_processors/sql/bigquery.py
airbyte/_processors/sql/duckdb.py
airbyte/_processors/sql/motherduck.py
airbyte/_processors/sql/postgres.py
airbyte/_processors/sql/snowflake.py
airbyte/_util/__init__.py
airbyte/_util/api_duck_types.py
airbyte/_util/api_imports.py
airbyte/_util/api_util.py
airbyte/_util/connector_info.py
airbyte/_util/document_rendering.py
airbyte/_util/hashing.py
airbyte/_util/meta.py
airbyte/_util/name_normalizers.py
airbyte/_util/pip_util.py
airbyte/_util/telemetry.py
airbyte/_util/temp_files.py
airbyte/_util/venv_util.py
airbyte/_writers/__init__.py
airbyte/_writers/base.py
airbyte/_writers/file_writers.py
airbyte/_writers/jsonl.py
airbyte/caches/__init__.py
airbyte/caches/_catalog_backend.py
airbyte/caches/_state_backend.py
airbyte/caches/_state_backend_base.py
airbyte/caches/base.py
airbyte/caches/bigquery.py
airbyte/caches/duckdb.py
airbyte/caches/generic.py
airbyte/caches/motherduck.py
airbyte/caches/postgres.py
airbyte/caches/snowflake.py
airbyte/caches/util.py
airbyte/callbacks.py
airbyte/cli.py
airbyte/cloud/__init__.py
airbyte/cloud/_destination_util.py
airbyte/cloud/connections.py
airbyte/cloud/constants.py
airbyte/cloud/experimental.py
airbyte/cloud/sync_results.py
airbyte/cloud/workspaces.py
airbyte/constants.py
airbyte/datasets/__init__.py
airbyte/datasets/_base.py
airbyte/datasets/_lazy.py
airbyte/datasets/_map.py
airbyte/datasets/_sql.py
airbyte/destinations/__init__.py
airbyte/destinations/base.py
airbyte/destinations/util.py
airbyte/documents.py
airbyte/exceptions.py
airbyte/experimental/__init__.py
airbyte/logs.py
airbyte/progress.py
airbyte/py.typed
pyairbyte_flowfile-0.20.2.dist-info/LICENSE.md
pyairbyte_flowfile-0.20.2.dist-info/METADATA
pyairbyte_flowfile-0.20.2.dist-info/WHEEL
pyairbyte_flowfile-0.20.2.dist-info/entry_points.txt
pyairbyte_flowfile-0.20.2.dist-info/RECORD
