Metadata-Version: 2.1
Name: pyairbyte-flowfile
Version: 0.20.2
Summary: PyAirbyte for Flowfile
Author: Airbyte
Author-email: contact@airbyte.io
Requires-Python: >=3.10,<3.13
Classifier: Programming Language :: Python :: 3
Classifier: Programming Language :: Python :: 3.10
Classifier: Programming Language :: Python :: 3.11
Classifier: Programming Language :: Python :: 3.12
Requires-Dist: airbyte-api (>=0.49.2,<0.50.0)
Requires-Dist: airbyte-cdk (>=6.6.4,<7.0.0,!=6.7.0rc1,!=6.7.0rc2)
Requires-Dist: airbyte-protocol-models-pdv2 (>=0.13.0,<0.14.0)
Requires-Dist: duckdb (>=1.1.0,<2.0.0)
Requires-Dist: duckdb-engine (>=0.13.2,<0.14.0)
Requires-Dist: google-auth (>=2.27.0,<3.0)
Requires-Dist: google-cloud-bigquery (>=3.12.0,<4.0)
Requires-Dist: google-cloud-bigquery-storage (>=2.25.0,<3.0.0)
Requires-Dist: google-cloud-secret-manager (>=2.17.0,<3.0.0)
Requires-Dist: grpcio (>=1.65.0,<2.0.0)
Requires-Dist: jsonschema (>=3.2.0,<5.0)
Requires-Dist: numpy (<2.0)
Requires-Dist: orjson (>=3.10,<4.0)
Requires-Dist: overrides (>=7.4.0,<8.0.0)
Requires-Dist: pandas (>=1.5.3,<3.0)
Requires-Dist: pendulum (<=3.0.0)
Requires-Dist: psycopg2-binary (>=2.9.9,<3.0.0)
Requires-Dist: psycopg[binary,pool] (>=3.1.19,<4.0.0)
Requires-Dist: pyarrow (>=16.1,<20.0)
Requires-Dist: pydantic (>=2.0,<=3.0)
Requires-Dist: pyiceberg (>=0.6.1,<0.7.0)
Requires-Dist: python-dotenv (>=1.0.1,<2.0.0)
Requires-Dist: python-ulid (>=3.0.0,<4.0.0)
Requires-Dist: requests (<=2.32.2)
Requires-Dist: rich (>=13.7.0,<14.0.0)
Requires-Dist: snowflake-connector-python (>=3.12.2,<4.0.0)
Requires-Dist: snowflake-sqlalchemy (>=1.6.1,<2.0.0)
Requires-Dist: sqlalchemy (>=1.4.51,!=2.0.36,<3.0)
Requires-Dist: sqlalchemy-bigquery (==1.12.0) ; python_version < "3.13"
Requires-Dist: structlog (>=24.4.0,<25.0.0)
Requires-Dist: types-pyyaml (>=6.0.12.12,<7.0.0.0)
Requires-Dist: uuid7 (>=0.1.0,<0.2.0)
